{
  "posts": [
    {
      "id": "t3_1t70g5d",
      "title": "Fuck Parkinsons",
      "subreddit": "r/BacktotheFuture",
      "author": "lucymainstreet",
      "permalink": "https://www.reddit.com/r/BacktotheFuture/comments/1t70g5d/fuck_parkinsons/",
      "created_utc": 1778224170,
      "score": 1404,
      "num_comments": 41,
      "upvote_ratio": 0.99,
      "engagement": 1486,
      "momentum": 132.2,
      "normalized_engagement": 1,
      "normalized_momentum": 1,
      "composite_score": 1,
      "timeAgo": "11 hours ago"
    },
    {
      "id": "t3_1t7b19l",
      "title": "Update from ROUTE 66 Parkinson's team (riding from Chicago to Phoenix)",
      "subreddit": "r/recumbent",
      "author": "ParkieDude",
      "permalink": "https://www.reddit.com/r/recumbent/comments/1t7b19l/update_from_route_66_parkinsons_team_riding_from/",
      "created_utc": 1778253588,
      "score": 21,
      "num_comments": 2,
      "upvote_ratio": 1,
      "engagement": 25,
      "momentum": 8.2,
      "normalized_engagement": 0.01616161616161616,
      "normalized_momentum": 0.061317183951551855,
      "composite_score": 0.039,
      "timeAgo": "3 hours ago"
    },
    {
      "id": "t3_1t7b7ky",
      "title": "Update: Route 66 Team, riding from UTAH to Phoenix World Parkinson's Congress",
      "subreddit": "r/Parkinsons",
      "author": "ParkieDude",
      "permalink": "https://www.reddit.com/r/Parkinsons/comments/1t7b7ky/update_route_66_team_riding_from_utah_to_phoenix/",
      "created_utc": 1778253973,
      "score": 19,
      "num_comments": 2,
      "upvote_ratio": 0.93,
      "engagement": 23,
      "momentum": 7.8,
      "normalized_engagement": 0.014814814814814815,
      "normalized_momentum": 0.05828917486752461,
      "composite_score": 0.037,
      "timeAgo": "2 hours ago"
    },
    {
      "id": "t3_1t7bt6v",
      "title": "I feel in over my head -- 33F, dad with Parkinsons, assisted living?",
      "subreddit": "r/AgingParents",
      "author": "epaarepa",
      "permalink": "https://www.reddit.com/r/AgingParents/comments/1t7bt6v/i_feel_in_over_my_head_33f_dad_with_parkinsons/",
      "created_utc": 1778255250,
      "score": 5,
      "num_comments": 6,
      "upvote_ratio": 1,
      "engagement": 17,
      "momentum": 6.5,
      "normalized_engagement": 0.010774410774410775,
      "normalized_momentum": 0.04844814534443604,
      "composite_score": 0.03,
      "timeAgo": "2 hours ago"
    }
  ],
  "totalScanned": 17,
  "fetchedAt": "2026-05-08T18:23:43.823Z",
  "fetchTime": 23.6
}