{
  "posts": [
    {
      "id": "t3_1t70g5d",
      "title": "Fuck Parkinsons",
      "subreddit": "r/BacktotheFuture",
      "author": "lucymainstreet",
      "permalink": "https://www.reddit.com/r/BacktotheFuture/comments/1t70g5d/fuck_parkinsons/",
      "created_utc": 1778224170,
      "score": 2445,
      "num_comments": 64,
      "upvote_ratio": 0.99,
      "engagement": 2573,
      "momentum": 118.2,
      "normalized_engagement": 1,
      "normalized_momentum": 1,
      "composite_score": 1,
      "timeAgo": "21 hours ago"
    },
    {
      "id": "t3_1t7b7ky",
      "title": "Update: Route 66 Team, riding from UTAH to Phoenix World Parkinson's Congress",
      "subreddit": "r/Parkinsons",
      "author": "ParkieDude",
      "permalink": "https://www.reddit.com/r/Parkinsons/comments/1t7b7ky/update_route_66_team_riding_from_utah_to_phoenix/",
      "created_utc": 1778253973,
      "score": 40,
      "num_comments": 5,
      "upvote_ratio": 0.96,
      "engagement": 50,
      "momentum": 3.7,
      "normalized_engagement": 0.019051321928460343,
      "normalized_momentum": 0.030482641828958507,
      "composite_score": 0.025,
      "timeAgo": "13 hours ago"
    },
    {
      "id": "t3_1t7b19l",
      "title": "Update from ROUTE 66 Parkinson's team (riding from Chicago to Phoenix)",
      "subreddit": "r/recumbent",
      "author": "ParkieDude",
      "permalink": "https://www.reddit.com/r/recumbent/comments/1t7b19l/update_from_route_66_parkinsons_team_riding_from/",
      "created_utc": 1778253588,
      "score": 44,
      "num_comments": 3,
      "upvote_ratio": 0.99,
      "engagement": 50,
      "momentum": 3.7,
      "normalized_engagement": 0.019051321928460343,
      "normalized_momentum": 0.030482641828958507,
      "composite_score": 0.025,
      "timeAgo": "13 hours ago"
    },
    {
      "id": "t3_1t73ige",
      "title": "Sleep problems getting worse after diagnosis",
      "subreddit": "r/Parkinsons",
      "author": "Traditional-Union128",
      "permalink": "https://www.reddit.com/r/Parkinsons/comments/1t73ige/sleep_problems_getting_worse_after_diagnosis/",
      "created_utc": 1778234662,
      "score": 9,
      "num_comments": 16,
      "upvote_ratio": 0.85,
      "engagement": 41,
      "momentum": 2.2,
      "normalized_engagement": 0.015552099533437015,
      "normalized_momentum": 0.017781541066892465,
      "composite_score": 0.017,
      "timeAgo": "18 hours ago"
    }
  ],
  "totalScanned": 16,
  "fetchedAt": "2026-05-09T04:56:01.207Z",
  "fetchTime": 23.2
}