{
  "posts": [
    {
      "id": "t3_1t4k2jn",
      "title": "Whats the deal with Boyds Parkinson's? I liked it for the plot and it hasnt been mentioned in forever, he was going downhill pretty quick as far as symptoms. And now he's just all better?",
      "subreddit": "r/FromSeries",
      "author": "Difficult_Wolf_",
      "permalink": "https://www.reddit.com/r/FromSeries/comments/1t4k2jn/whats_the_deal_with_boyds_parkinsons_i_liked_it/",
      "created_utc": 1777997594,
      "score": 163,
      "num_comments": 118,
      "upvote_ratio": 0.89,
      "engagement": 399,
      "momentum": 50.1,
      "normalized_engagement": 1,
      "normalized_momentum": 1,
      "composite_score": 1,
      "timeAgo": "7 hours ago"
    },
    {
      "id": "t3_1t4ec9q",
      "title": "Scientists have identified a protective brain pathway that may help slow the progression of Parkinson’s disease by strengthening the brain’s own dopamine‑producing neurons, but the positive effect was only observed in females",
      "subreddit": "r/science",
      "author": "sr_local",
      "permalink": "https://www.reddit.com/r/science/comments/1t4ec9q/scientists_have_identified_a_protective_brain/",
      "created_utc": 1777984982,
      "score": 328,
      "num_comments": 3,
      "upvote_ratio": 0.99,
      "engagement": 334,
      "momentum": 29.1,
      "normalized_engagement": 0.8366834170854272,
      "normalized_momentum": 0.58,
      "composite_score": 0.708,
      "timeAgo": "11 hours ago"
    },
    {
      "id": "t3_1t4i1jv",
      "title": "My deaf dragonborn now has Parkinson.",
      "subreddit": "r/skyrim",
      "author": "Ph33r-Enigma",
      "permalink": "https://www.reddit.com/r/skyrim/comments/1t4i1jv/my_deaf_dragonborn_now_has_parkinson/",
      "created_utc": 1777993312,
      "score": 109,
      "num_comments": 16,
      "upvote_ratio": 0.89,
      "engagement": 141,
      "momentum": 15.4,
      "normalized_engagement": 0.35175879396984927,
      "normalized_momentum": 0.306,
      "composite_score": 0.329,
      "timeAgo": "9 hours ago"
    },
    {
      "id": "t3_1t4rij1",
      "title": "Psych and Fatigue",
      "subreddit": "r/Parkinsons",
      "author": "Whatstheplan150",
      "permalink": "https://www.reddit.com/r/Parkinsons/comments/1t4rij1/psych_and_fatigue/",
      "created_utc": 1778013090,
      "score": 11,
      "num_comments": 4,
      "upvote_ratio": 1,
      "engagement": 19,
      "momentum": 5.2,
      "normalized_engagement": 0.04522613065326633,
      "normalized_momentum": 0.10200000000000001,
      "composite_score": 0.074,
      "timeAgo": "3 hours ago"
    }
  ],
  "totalScanned": 17,
  "fetchedAt": "2026-05-06T00:10:45.902Z",
  "fetchTime": 22
}