{
  "posts": [
    {
      "id": "t3_1slr6sx",
      "title": "Alberta’s plan to curb MAID access worries ALS, Parkinson’s advocates",
      "subreddit": "r/Edmonton",
      "author": "GeekyGlobalGal",
      "permalink": "https://www.reddit.com/r/Edmonton/comments/1slr6sx/albertas_plan_to_curb_maid_access_worries_als/",
      "created_utc": 1776214560,
      "score": 19,
      "num_comments": 1,
      "upvote_ratio": 0.88,
      "engagement": 21,
      "momentum": 35,
      "normalized_engagement": 0.8695652173913043,
      "normalized_momentum": 1,
      "composite_score": 0.935,
      "timeAgo": "35 minutes ago"
    },
    {
      "id": "t3_1slq9l7",
      "title": "The origin of Gerard and Mikey's photoshoot in the woods: Parkinson's disease awareness.",
      "subreddit": "r/ThePaperKingdomMCR",
      "author": "Ohnoblu",
      "permalink": "https://www.reddit.com/r/ThePaperKingdomMCR/comments/1slq9l7/the_origin_of_gerard_and_mikeys_photoshoot_in_the/",
      "created_utc": 1776212117,
      "score": 16,
      "num_comments": 4,
      "upvote_ratio": 1,
      "engagement": 24,
      "momentum": 18.8,
      "normalized_engagement": 1,
      "normalized_momentum": 0.5371428571428571,
      "composite_score": 0.769,
      "timeAgo": "1 hour ago"
    },
    {
      "id": "t3_1sll36q",
      "title": "I'm in diagnosis limbo...",
      "subreddit": "r/Parkinsons",
      "author": "MrDopey_Monkey",
      "permalink": "https://www.reddit.com/r/Parkinsons/comments/1sll36q/im_in_diagnosis_limbo/",
      "created_utc": 1776199690,
      "score": 7,
      "num_comments": 5,
      "upvote_ratio": 1,
      "engagement": 17,
      "momentum": 3.6,
      "normalized_engagement": 0.6956521739130435,
      "normalized_momentum": 0.10285714285714286,
      "composite_score": 0.399,
      "timeAgo": "4 hours ago"
    },
    {
      "id": "t3_1slkr9l",
      "title": "Hello medicos. I need best neurologist ( treatment for vascular Parkinson) to treat my father in Hyderabad. Can anyone suggest or guide me guys .",
      "subreddit": "r/telugumedschool",
      "author": "Realistic_Advisor_60",
      "permalink": "https://www.reddit.com/r/telugumedschool/comments/1slkr9l/hello_medicos_i_need_best_neurologist_treatment/",
      "created_utc": 1776198939,
      "score": 5,
      "num_comments": 3,
      "upvote_ratio": 1,
      "engagement": 11,
      "momentum": 2.2,
      "normalized_engagement": 0.43478260869565216,
      "normalized_momentum": 0.06285714285714286,
      "composite_score": 0.249,
      "timeAgo": "4 hours ago"
    }
  ],
  "totalScanned": 16,
  "fetchedAt": "2026-04-15T01:31:59.294Z",
  "fetchTime": 22.2
}